[
  {
    "chainId": 10,
    "address": "0x5b977577eb8a480f63e11fc615d6753adb8652ae",
    "price": 4735.216353700223,
    "time": 1756113796298,
    "source": "yearn"
  },
  {
    "chainId": 10,
    "address": "0x7d2382b1f8af621229d33464340541db362b4907",
    "price": 0.7574240908883555,
    "time": 1756113796298,
    "source": "yearn"
  },
  {
    "chainId": 10,
    "address": "0xad17a225074191d5c8a37b50fda1ae278a2ee6a2",
    "price": 1.0725566757070002,
    "time": 1756113796298,
    "source": "yearn"
  },
  {
    "chainId": 10,
    "address": "0x65343f414ffd6c97b0f6add33d16f6845ac22bac",
    "price": 0.8332188493770413,
    "time": 1756113796299,
    "source": "yearn"
  },
  {
    "chainId": 10,
    "address": "0xfaee21d0f0af88ee72bb6d68e54a90e6ec2616de",
    "price": 0.4851380609999999,
    "time": 1756113796299,
    "source": "yearn"
  },
  {
    "chainId": 10,
    "address": "0x7edf16076e56fa4c111055fba1ff5556b8757cfb",
    "price": 111809.3299072,
    "time": 1756113796300,
    "source": "yearn"
  },
  {
    "chainId": 10,
    "address": "0x2a90f479002daae9934c3a70ebb6e8dbeb46292b",
    "price": 1.0799318334317458,
    "time": 1756113796300,
    "source": "yearn"
  },
  {
    "chainId": 10,
    "address": "0x6759574667896a453304897993d61f00fdc7214d",
    "price": 0.4173314014885,
    "time": 1756113796300,
    "source": "yearn"
  },
  {
    "chainId": 10,
    "address": "0xb4e4cfa9971c7e1069685771dab61ca56e72e5c3",
    "price": 1.030805717999919,
    "time": 1756113796300,
    "source": "yearn"
  },
  {
    "chainId": 10,
    "address": "0x0a2f234ad2e5e9047067904a9d37d0cd02b80d12",
    "price": 112139.6704128,
    "time": 1756113796300,
    "source": "yearn"
  },
  {
    "chainId": 10,
    "address": "0x4c8b1958b09b3bde714f68864bcc3a74eaf1a23d",
    "price": 1.03554556029,
    "time": 1756113796300,
    "source": "yearn"
  },
  {
    "chainId": 10,
    "address": "0xc328d83883f5f90e1108d4dd7a18ffca17ae74d7",
    "price": 1.0513160694627877,
    "time": 1756113796300,
    "source": "yearn"
  },
  {
    "chainId": 10,
    "address": "0xfbef713696465ddab297164c3b6a0122d92a3bac",
    "price": 1.0594994309235757,
    "time": 1756113796300,
    "source": "yearn"
  },
  {
    "chainId": 10,
    "address": "0xacb84e988327d7acc843d6f1389f99f5f864529a",
    "price": 4704.7746249471475,
    "time": 1756113796300,
    "source": "yearn"
  },
  {
    "chainId": 10,
    "address": "0xa318373f0424ef0257b5b75460548d6d34947d97",
    "price": 1.0046063011699822,
    "time": 1756113796300,
    "source": "yearn"
  },
  {
    "chainId": 10,
    "address": "0x0fbea11f39be912096cec5ce22f46908b5375c19",
    "price": 0.979427,
    "time": 1756113796300,
    "source": "yearn"
  },
  {
    "chainId": 10,
    "address": "0x7427c44d2824e4df3b518822f2b11154e937efea",
    "price": 0.979427,
    "time": 1756113796300,
    "source": "yearn"
  },
  {
    "chainId": 10,
    "address": "0xb6fb466c982c04aba1bdbea386c1af2a47b82e6d",
    "price": 4604.05,
    "time": 1756113796300,
    "source": "yearn"
  },
  {
    "chainId": 10,
    "address": "0xb151887bbba5585119c91914e740613ea16e7afd",
    "price": 0.979427,
    "time": 1756113796300,
    "source": "yearn"
  },
  {
    "chainId": 10,
    "address": "0xe496a661ca61ea424c0626119a5ea1f268d958fc",
    "price": 0.979427,
    "time": 1756113796301,
    "source": "yearn"
  },
  {
    "chainId": 10,
    "address": "0x5e70e0ede43373bd9cf4bc85199d424acf0241ef",
    "price": 1.1475420490371393,
    "time": 1756113796301,
    "source": "yearn"
  },
  {
    "chainId": 10,
    "address": "0x6554aa3acf15cce6206470cc29416304f16b55d9",
    "price": 0.979427,
    "time": 1756113796301,
    "source": "yearn"
  },
  {
    "chainId": 10,
    "address": "0xed5d83bb6af23bcb05c144dc816f45a389d622a0",
    "price": 0.999571,
    "time": 1756113796301,
    "source": "yearn"
  },
  {
    "chainId": 10,
    "address": "0x6884bd538db61a626da0a05e10807bfc5aea2b32",
    "price": 111680,
    "time": 1756113796301,
    "source": "yearn"
  },
  {
    "chainId": 10,
    "address": "0xa628c54c850ff1077b5c954491d19ecce7e321ff",
    "price": 4696.3031746052175,
    "time": 1756113796301,
    "source": "yearn"
  },
  {
    "chainId": 10,
    "address": "0x4262150e8cd1c3d5739aef7fff0dc39d6d90ab70",
    "price": 0.999462,
    "time": 1756113796301,
    "source": "yearn"
  },
  {
    "chainId": 10,
    "address": "0x3fc986cc3b44bad5baf1e47031055cf69466ad57",
    "price": 0.979427,
    "time": 1756113796301,
    "source": "yearn"
  },
  {
    "chainId": 10,
    "address": "0x9c839cb0562785e2eb50c0e0fdd12f6da8bddb23",
    "price": 0.999571,
    "time": 1756113796301,
    "source": "yearn"
  },
  {
    "chainId": 10,
    "address": "0xe5c30a5083f5a5ca08a9896cd0fe807acf925271",
    "price": 111680,
    "time": 1756113796301,
    "source": "yearn"
  },
  {
    "chainId": 10,
    "address": "0x4200000000000000000000000000000000000006",
    "price": 4604.05,
    "time": 1756113796301,
    "source": "coingecko"
  },
  {
    "chainId": 10,
    "address": "0x4200000000000000000000000000000000000042",
    "price": 0.741878,
    "time": 1756113796301,
    "source": "coingecko"
  },
  {
    "chainId": 10,
    "address": "0x7f5c764cbc14f9669b88837ca1490cca17c31607",
    "price": 0.999571,
    "time": 1756113796301,
    "source": "coingecko"
  },
  {
    "chainId": 10,
    "address": "0xda10009cbd5d07dd0cecc66161fc93d7c9000da1",
    "price": 0.999462,
    "time": 1756113796301,
    "source": "coingecko"
  },
  {
    "chainId": 10,
    "address": "0x94b008aa00579c1307b0ef2c499ad98a8ce58e58",
    "price": 1.003,
    "time": 1756113796301,
    "source": "coingecko"
  },
  {
    "chainId": 10,
    "address": "0x68f180fcce6836688e9084f035309e29bf0a2095",
    "price": 111680,
    "time": 1756113796301,
    "source": "coingecko"
  },
  {
    "chainId": 10,
    "address": "0x8c6f28f2f1a3c87f0f938b96d27520d9751ec8d9",
    "price": 0.979427,
    "time": 1756113796301,
    "source": "coingecko"
  },
  {
    "chainId": 10,
    "address": "0xdfa46478f9e5ea86d57387849598dbfb2e964b02",
    "price": 0.411418,
    "time": 1756113796301,
    "source": "coingecko"
  },
  {
    "chainId": 10,
    "address": "0x7bc5728bc2b59b45a58d9a576e2ffc5f0505b35e",
    "price": 1.030805717999919,
    "time": 1756113796301,
    "source": "coingecko"
  },
  {
    "chainId": 10,
    "address": "0x68f180fcce6836688e9084f035309e29bf0a2095",
    "price": 111680,
    "time": 1756113796301,
    "source": "coingecko"
  },
  {
    "chainId": 10,
    "address": "0x7f5c764cbc14f9669b88837ca1490cca17c31607",
    "price": 0.999571,
    "time": 1756113796301,
    "source": "coingecko"
  },
  {
    "chainId": 10,
    "address": "0x8c6f28f2f1a3c87f0f938b96d27520d9751ec8d9",
    "price": 0.979427,
    "time": 1756113796301,
    "source": "coingecko"
  },
  {
    "chainId": 10,
    "address": "0xda10009cbd5d07dd0cecc66161fc93d7c9000da1",
    "price": 0.999462,
    "time": 1756113796301,
    "source": "coingecko"
  },
  {
    "chainId": 10,
    "address": "0x8c6f28f2f1a3c87f0f938b96d27520d9751ec8d9",
    "price": 0.979427,
    "time": 1756113796301,
    "source": "coingecko"
  },
  {
    "chainId": 10,
    "address": "0x4200000000000000000000000000000000000006",
    "price": 4604.05,
    "time": 1756113796301,
    "source": "coingecko"
  },
  {
    "chainId": 10,
    "address": "0xda10009cbd5d07dd0cecc66161fc93d7c9000da1",
    "price": 0.999462,
    "time": 1756113796301,
    "source": "coingecko"
  },
  {
    "chainId": 10,
    "address": "0x8c6f28f2f1a3c87f0f938b96d27520d9751ec8d9",
    "price": 0.979427,
    "time": 1756113796301,
    "source": "coingecko"
  },
  {
    "chainId": 10,
    "address": "0x8c6f28f2f1a3c87f0f938b96d27520d9751ec8d9",
    "price": 0.979427,
    "time": 1756113796301,
    "source": "coingecko"
  },
  {
    "chainId": 10,
    "address": "0x4200000000000000000000000000000000000006",
    "price": 4604.05,
    "time": 1756113796301,
    "source": "coingecko"
  },
  {
    "chainId": 10,
    "address": "0x8c6f28f2f1a3c87f0f938b96d27520d9751ec8d9",
    "price": 0.979427,
    "time": 1756113796301,
    "source": "coingecko"
  },
  {
    "chainId": 10,
    "address": "0x8c6f28f2f1a3c87f0f938b96d27520d9751ec8d9",
    "price": 0.979427,
    "time": 1756113796301,
    "source": "coingecko"
  },
  {
    "chainId": 10,
    "address": "0x061b87122ed14b9526a813209c8a59a633257bab",
    "price": 1.0771816982876656,
    "time": 1756113796301,
    "source": "coingecko"
  },
  {
    "chainId": 10,
    "address": "0x8c6f28f2f1a3c87f0f938b96d27520d9751ec8d9",
    "price": 0.979427,
    "time": 1756113796301,
    "source": "coingecko"
  },
  {
    "chainId": 10,
    "address": "0x7f5c764cbc14f9669b88837ca1490cca17c31607",
    "price": 0.999571,
    "time": 1756113796301,
    "source": "coingecko"
  },
  {
    "chainId": 10,
    "address": "0x68f180fcce6836688e9084f035309e29bf0a2095",
    "price": 111680,
    "time": 1756113796301,
    "source": "coingecko"
  },
  {
    "chainId": 10,
    "address": "0x4200000000000000000000000000000000000006",
    "price": 4604.05,
    "time": 1756113796301,
    "source": "coingecko"
  },
  {
    "chainId": 10,
    "address": "0xda10009cbd5d07dd0cecc66161fc93d7c9000da1",
    "price": 0.999462,
    "time": 1756113796301,
    "source": "coingecko"
  },
  {
    "chainId": 10,
    "address": "0x8c6f28f2f1a3c87f0f938b96d27520d9751ec8d9",
    "price": 0.979427,
    "time": 1756113796301,
    "source": "coingecko"
  },
  {
    "chainId": 10,
    "address": "0x7f5c764cbc14f9669b88837ca1490cca17c31607",
    "price": 0.999571,
    "time": 1756113796301,
    "source": "coingecko"
  },
  {
    "chainId": 10,
    "address": "0x68f180fcce6836688e9084f035309e29bf0a2095",
    "price": 111680,
    "time": 1756113796301,
    "source": "coingecko"
  }
]